storages/__init__.py
storages/types.py
storages/async_storages/__init__.py
storages/async_storages/base_nosql_storage.py
storages/async_storages/json_storage.py
storages/async_storages/pickle_storage.py
storages/async_storages/redis_storage.py
storages/sync_storages/__init__.py
storages/sync_storages/base_nosql_storage.py
storages/sync_storages/json_storage.py
storages/sync_storages/pickle_storage.py
storages/sync_storages/redis_storage.py
pyStorages-0.0.6.dist-info/LICENSE
pyStorages-0.0.6.dist-info/METADATA
pyStorages-0.0.6.dist-info/WHEEL
pyStorages-0.0.6.dist-info/top_level.txt
pyStorages-0.0.6.dist-info/RECORD
