Metadata-Version: 2.1
Name: pyStorages
Version: 0.0.6
Summary: Simple data storages package
Author-email: Konstantin Ostashenko <ostashenkokd@gmail.com>
Project-URL: Homepage, https://github.com/Cub11k/pyStorages
Classifier: Programming Language :: Python :: 3
Classifier: License :: OSI Approved :: GNU General Public License v3 (GPLv3)
Classifier: Operating System :: OS Independent
Requires-Python: >=3.7
License-File: LICENSE
Requires-Dist: aiofiles (>=22.1.0)
Provides-Extra: aioredis
Requires-Dist: aioredis (>=2.0.0) ; extra == 'aioredis'
Provides-Extra: redis
Requires-Dist: redis (>=3.4.1) ; extra == 'redis'
